lsyiot_ys7_sdk/__init__.py
lsyiot_ys7_sdk/api.py
lsyiot_ys7_sdk/exceptions.py
lsyiot_ys7_sdk/models.py
lsyiot_ys7_sdk-1.1.0.dist-info/licenses/LICENSE
lsyiot_ys7_sdk-1.1.0.dist-info/METADATA
lsyiot_ys7_sdk-1.1.0.dist-info/WHEEL
lsyiot_ys7_sdk-1.1.0.dist-info/top_level.txt
lsyiot_ys7_sdk-1.1.0.dist-info/RECORD
