Metadata-Version: 2.4
Name: lsyiot-ys7-sdk
Version: 1.1.0
Summary: 萤石云开放平台 Python SDK - 支持云台控制、设备管理、播放地址获取等功能
Author-email: fhp <chinafengheping@outlook.com>
License: Apache-2.0
Project-URL: Homepage, https://github.com/9kl/lsyiot_ys7_sdk
Project-URL: Documentation, https://github.com/9kl/lsyiot_ys7_sdk#readme
Project-URL: Repository, https://github.com/9kl/lsyiot_ys7_sdk.git
Project-URL: Bug Tracker, https://github.com/9kl/lsyiot_ys7_sdk/issues
Project-URL: Changelog, https://github.com/9kl/lsyiot_ys7_sdk/releases
Keywords: ys7,ezviz,yingshiyun,萤石云,hikvision,ipc,ptz,surveillance,sdk,iot
Classifier: Development Status :: 5 - Production/Stable
Classifier: Intended Audience :: Developers
Classifier: License :: OSI Approved :: Apache Software License
Classifier: Operating System :: OS Independent
Classifier: Programming Language :: Python :: 3
Classifier: Programming Language :: Python :: 3.8
Classifier: Programming Language :: Python :: 3.9
Classifier: Programming Language :: Python :: 3.10
Classifier: Programming Language :: Python :: 3.11
Classifier: Programming Language :: Python :: 3.12
Classifier: Programming Language :: Python :: 3.13
Classifier: Topic :: Software Development :: Libraries :: Python Modules
Classifier: Topic :: Multimedia :: Video
Classifier: Topic :: System :: Networking
Classifier: Topic :: Home Automation
Classifier: Typing :: Typed
Requires-Python: >=3.8
License-File: LICENSE
Requires-Dist: requests>=2.25.0
Provides-Extra: dev
Requires-Dist: pytest>=7.0.0; extra == "dev"
Requires-Dist: pytest-cov>=4.0.0; extra == "dev"
Requires-Dist: black>=23.0.0; extra == "dev"
Requires-Dist: isort>=5.12.0; extra == "dev"
Requires-Dist: mypy>=1.0.0; extra == "dev"
Requires-Dist: types-requests>=2.28.0; extra == "dev"
Dynamic: license-file
